modely/__init__.py
modely/hf/__init__.py
modely/modelscope/__init__.py
modely_ai-0.1.1.dist-info/licenses/LICENSE
modely_ai-0.1.1.dist-info/METADATA
modely_ai-0.1.1.dist-info/WHEEL
modely_ai-0.1.1.dist-info/entry_points.txt
modely_ai-0.1.1.dist-info/top_level.txt
modely_ai-0.1.1.dist-info/RECORD
