Metadata-Version: 2.4
Name: modely-ai
Version: 0.1.1
Summary: AI models download in one command
Requires-Python: >=3.10
License-File: LICENSE
Requires-Dist: requests>=2.25.0
Requires-Dist: tqdm>=4.62.0
Dynamic: license-file
